otyg_risk_base/__init__.py
otyg_risk_base/hybrid.py
otyg_risk_base/montecarlo.py
otyg_risk_base/qualitative_risk.py
otyg_risk_base/qualitative_scale.py
otyg_risk_base/quantitative_risk.py
otyg_risk_base/utils.py
otyg_risk_base-1.2.1.dist-info/METADATA
otyg_risk_base-1.2.1.dist-info/WHEEL
otyg_risk_base-1.2.1.dist-info/licenses/LICENSE
otyg_risk_base-1.2.1.dist-info/RECORD
