Metadata-Version: 2.4
Name: otyg_risk_base
Version: 1.2.1
Summary: Base classes for risk calculations
Project-URL: Homepage, https://github.com/Otyg/riskBase
Project-URL: Issues, https://github.com/Otyg/riskBase/issues
Author-email: Martin Vesterlund <vesterlund.martin@gmail.com>
License-Expression: BSD-3-Clause
License-File: LICENSE
Classifier: Operating System :: OS Independent
Classifier: Programming Language :: Python :: 3
Requires-Python: >=3.9
Requires-Dist: numpy>=2.2.6
